beatserver/__init__.py
beatserver/apps.py
beatserver/parser.py
beatserver/server.py
beatserver/tests.py
beatserver/management/__init__.py
beatserver/management/commands/__init__.py
beatserver/management/commands/beatserver.py
beatserver-0.0.8.dist-info/LICENSE
beatserver-0.0.8.dist-info/METADATA
beatserver-0.0.8.dist-info/WHEEL
beatserver-0.0.8.dist-info/top_level.txt
beatserver-0.0.8.dist-info/RECORD
