Metadata-Version: 2.1
Name: beatserver
Version: 0.0.8
Summary: Beat Server is is a scheduler
Home-page: https://github.com/rajasimon/beatserver
Author: Raja Simon
Author-email: rajasimon@icloud.com
License: MIT
License-File: LICENSE
Requires-Dist: channels (>=1.1.8.1)
Requires-Dist: croniter (>=0.3.30)
